jsoncf/__init__.py
jsoncf/clipboard/__init__.py
jsoncf/clipboard/__main__.py
jsoncf/main.py
jsoncf-0.0.6.dist-info/entry_points.txt
jsoncf-0.0.6.dist-info/LICENSE
jsoncf-0.0.6.dist-info/WHEEL
jsoncf-0.0.6.dist-info/METADATA
jsoncf-0.0.6.dist-info/RECORD
