Metadata-Version: 2.1
Name: jsoncf
Version: 0.0.6
Summary: prettify json data from clipboard
License: MIT
Author: idlewith
Author-email: newellzhou@163.com
Requires-Python: >=3.7,<4.0
Classifier: License :: OSI Approved :: MIT License
Classifier: Programming Language :: Python :: 3
Classifier: Programming Language :: Python :: 3.7
Classifier: Programming Language :: Python :: 3.8
Classifier: Programming Language :: Python :: 3.9
Classifier: Programming Language :: Python :: 3.10
